satlite/__init__.py
satlite/py.typed
satlite/application/env.py
satlite/application/plugin.py
satlite/application/config/litestar.py
satlite/application/config/mime_types.py
satlite/application/config/settings.py
satlite/application/config/defaults/__init__.py
satlite/application/config/defaults/cache.py
satlite/application/config/defaults/cors.py
satlite/application/config/defaults/csrf.py
satlite/application/config/defaults/openapi.py
satlite/application/config/defaults/signature_namespaces.py
satlite/application/config/defaults/structlog.py
satlite/application/config/defaults/vite.py
satlite/application/config/middleware/server.py
satlite/application/config/plugins/exceptions.py
satlite/middleware/authentication/__init__.py
satlite/middleware/authentication/inclusive_abstract_auth.py
satlite/utils/pretty_print.py
satlite/utils/typed_settings.py
satlite-0.6.1.dist-info/METADATA
satlite-0.6.1.dist-info/WHEEL
satlite-0.6.1.dist-info/RECORD
